multicastclient/__init__.py
multicastclient/client.py
multicastclient/minimal.py
multicastclient/multicasting.py
multicastclient/tiipclient.py
multicastclient-1.0.dist-info/LICENSE.txt
multicastclient-1.0.dist-info/METADATA
multicastclient-1.0.dist-info/RECORD
multicastclient-1.0.dist-info/WHEEL
multicastclient-1.0.dist-info/top_level.txt
